terminal_media_player/__init__.py
terminal_media_player/cli.py
terminal_media_player/player.py
terminal_media_player/utils.py
terminal_media_player-1.0.0.dist-info/licenses/LICENSE
terminal_media_player-1.0.0.dist-info/METADATA
terminal_media_player-1.0.0.dist-info/WHEEL
terminal_media_player-1.0.0.dist-info/entry_points.txt
terminal_media_player-1.0.0.dist-info/top_level.txt
terminal_media_player-1.0.0.dist-info/RECORD
